vtivrt/__init__.py
vtivrt/constants.py
vtivrt/packet.py
vtivrt/reader.py
vtivrt-1.0.0.dist-info/LICENSE
vtivrt-1.0.0.dist-info/METADATA
vtivrt-1.0.0.dist-info/WHEEL
vtivrt-1.0.0.dist-info/top_level.txt
vtivrt-1.0.0.dist-info/RECORD
